Workbook

Sheet Custo de Produção
A1: CUSTO DE PRODUÇÃO POR PRODUTO
A3: Produto:
A4: Unidades por lote: | B4: 30
A6: Categoria | B6: Item | C6: Custo do Lote (R$) | D6: Custo/Unidade
A7: Matéria-prima | B7: Ingrediente principal | C7: 0 | D7: =IF($B$4>0,C7/$B$4,0)
A8: Matéria-prima | B8: Ingrediente 2 | C8: 0 | D8: =IF($B$4>0,C8/$B$4,0)
A9: Matéria-prima | B9: Ingrediente 3 | C9: 0 | D9: =IF($B$4>0,C9/$B$4,0)
A10: Matéria-prima | B10: Ingrediente 4 | C10: 0 | D10: =IF($B$4>0,C10/$B$4,0)
A11: Matéria-prima | B11: Ingrediente 5 | C11: 0 | D11: =IF($B$4>0,C11/$B$4,0)
A12: Embalagem | B12: Pote / vidro / frasco | C12: 0 | D12: =IF($B$4>0,C12/$B$4,0)
A13: Embalagem | B13: Rótulo / etiqueta | C13: 0 | D13: =IF($B$4>0,C13/$B$4,0)
A14: Embalagem | B14: Tampa / lacre | C14: 0 | D14: =IF($B$4>0,C14/$B$4,0)
A15: Embalagem | B15: Caixa / embalagem externa | C15: 0 | D15: =IF($B$4>0,C15/$B$4,0)
A16: Energia | B16: Gás (proporcional ao lote) | C16: 0 | D16: =IF($B$4>0,C16/$B$4,0)
A17: Energia | B17: Energia elétrica | C17: 0 | D17: =IF($B$4>0,C17/$B$4,0)
A18: Mão de obra | B18: Horas × valor/hora | C18: 0 | D18: =IF($B$4>0,C18/$B$4,0)
... A20: Outros | B20: Perdas estimadas (5-10%) | C20: 0 | D20: =IF($B$4>0,C20/$B$4,0)
B21: TOTAL | C21: =SUM(C7:C20) | D21: =IF($B$4>0,C21/$B$4,0)

Sheet Formação de Preço
A1: FORMAÇÃO DE PREÇO — 3 MÉTODOS
A3: Custo por Unidade (CPU): | B3: ='Custo de Produção'!D21
A5: MÉTODO 1: MARKUP
A6: Multiplicador (2.0 a 4.0): | B6: 2.5
A7: Preço pelo Markup: | B7: =B3*B6 | C7: Margem: | D7: =IF(B7>0,(B7-B3)/B7,0)
A9: MÉTODO 2: MARGEM DE LUCRO
A10: Margem desejada (%): | B10: 60
A11: Preço pela Margem: | B11: =IF(B10<100,B3/(1-B10/100),0) | C11: Margem: | D11: =B10/100
A13: MÉTODO 3: BASEADO EM VALOR (recomendado)
A14: Preço que o mercado paga: | B14: 0
A15: Preço baseado em valor: | B15: =B14 | C15: Margem: | D15: =IF(B15>0,(B15-B3)/B15,0)
A17: COMPARAÇÃO
A18: Método | B18: Preço | C18: Margem Bruta | D18: Lucro/Unidade
A19: Markup | B19: =B7 | C19: =D7 | D19: =B7-B3
A20: Margem | B20: =B11 | C20: =D11 | D20: =B11-B3
A21: Valor | B21: =B15 | C21: =D15 | D21: =B15-B3
A23: Use o MAIOR valor entre os 3. Se o preço por valor é o maior, o mercado sustenta.

Sheet Simulador
A1: SIMULADOR DE FATURAMENTO MENSAL
A3: Preço unitário usado: | B3: =MAX('Formação de Preço'!B7,'Formação de Preço'!B11,'Formação de Preço'!B15)
A4: Custo unitário: | B4: ='Formação de Preço'!B3
A6: Cenário | B6: Unid/Mês | C6: Preço Unit. | D6: Faturamento | E6: Custo Total | F6: Lucro Bruto | G6: Margem %
A7: Conservador | B7: 0 | C7: =$B$3 | D7: =B7*C7 | E7: =B7*$B$4 | F7: =D7-E7 | G7: =IF(D7>0,F7/D7,0)
A8: Realista | B8: 0 | C8: =$B$3 | D8: =B8*C8 | E8: =B8*$B$4 | F8: =D8-E8 | G8: =IF(D8>0,F8/D8,0)
A9: Otimista | B9: 0 | C9: =$B$3 | D9: =B9*C9 | E9: =B9*$B$4 | F9: =D9-E9 | G9: =IF(D9>0,F9/D9,0)

Sheet Concorrentes
A1: COMPARATIVO DE CONCORRENTES
A3: Concorrente | B3: Produto | C3: Peso (g) | D3: Preço (R$) | E3: R$/100g | F3: Diferencial | G3: Canal
E4: =IF(C4>0,D4/(C4/100),0)
E5: =IF(C5>0,D5/(C5/100),0)
E6: =IF(C6>0,D6/(C6/100),0)
E7: =IF(C7>0,D7/(C7/100),0)
E8: =IF(C8>0,D8/(C8/100),0)
A9: SEU PRODUTO | B9: ='Custo de Produção'!B3 | D9: =MAX('Formação de Preço'!B7,'Formação de Preço'!B11,'Formação de Preço'!B15) | E9: =IF(C9>0,D9/(C9/100),0) | F9: Artesanal

Sheet Referência Markup
A1: REFERÊNCIA DE MARKUP POR CATEGORIA
A3: Categoria | B3: Mínimo | C3: Recomendado | D3: Premium | E3: Observação
A4: Geleias e Doces | B4: 2 | C4: 2.5 | D4: 3.5 | E4: Ingredientes raros ou orgânicos: premium
A5: Queijos Artesanais | B5: 2 | C5: 3 | D5: 4 | E5: Maturados e com IG: markup maior
A6: Molhos e Temperos | B6: 2.5 | C6: 3 | D6: 4 | E6: Pimentas especiais: markup alto
A7: Conservas | B7: 2 | C7: 2.5 | D7: 3 | E7: Em azeite premium: markup maior
A8: Pães e Fermentados | B8: 1.8 | C8: 2.5 | D8: 3 | E8: Massa madre / longa fermentação
A9: Mel e Derivados | B9: 2 | C9: 2.5 | D9: 3.5 | E9: Mel com IG ou orgânico: premium
A10: Embutidos | B10: 2 | C10: 2.5 | D10: 3.5 | E10: Curados e defumados: markup maior
A11: Cafés Gourmet | B11: 2.5 | C11: 3 | D11: 4.5 | E11: Microlotes e torras especiais
